[{"date":"2012-05-02","volume":8577224,"close":15.12,"clickCount":22982,"positiveCount":3,"negativeCount":6},{"date":"2012-05-03","volume":5980414,"close":15.2,"clickCount":16017,"positiveCount":2,"negativeCount":10},{"date":"2012-05-04","volume":6575433,"close":15.3,"clickCount":12149,"positiveCount":2,"negativeCount":6},{"date":"2012-05-07","volume":8600492,"close":15.03,"clickCount":30383,"positiveCount":3,"negativeCount":17},{"date":"2012-05-08","volume":15607080,"close":15.55,"clickCount":20540,"positiveCount":5,"negativeCount":9},{"date":"2012-05-09","volume":8932969,"close":15.07,"clickCount":28254,"positiveCount":8,"negativeCount":9},{"date":"2012-05-10","volume":7511506,"close":15.23,"clickCount":17087,"positiveCount":4,"negativeCount":16},{"date":"2012-05-11","volume":6097799,"close":15.11,"clickCount":19803,"positiveCount":7,"negativeCount":21},{"date":"2012-05-14","volume":4731678,"close":14.87,"clickCount":14237,"positiveCount":3,"negativeCount":11},{"date":"2012-05-15","volume":5037298,"close":14.8,"clickCount":13846,"positiveCount":6,"negativeCount":6},{"date":"2012-05-16","volume":4965788,"close":14.91,"clickCount":6731,"positiveCount":2,"negativeCount":4},{"date":"2012-05-17","volume":4514332,"close":15.12,"clickCount":9515,"positiveCount":5,"negativeCount":7},{"date":"2012-05-18","volume":14518300,"close":15.36,"clickCount":44882,"positiveCount":8,"negativeCount":23},{"date":"2012-05-21","volume":8265544,"close":15.29,"clickCount":23835,"positiveCount":6,"negativeCount":12},{"date":"2012-05-22","volume":5374349,"close":15.4,"clickCount":17543,"positiveCount":6,"negativeCount":10},{"date":"2012-05-23","volume":4777453,"close":15.21,"clickCount":11359,"positiveCount":5,"negativeCount":7},{"date":"2012-05-24","volume":5160457,"close":14.86,"clickCount":17193,"positiveCount":4,"negativeCount":16},{"date":"2012-05-25","volume":8359548,"close":14.16,"clickCount":11639,"positiveCount":3,"negativeCount":8},{"date":"2012-05-28","volume":7934863,"close":14.27,"clickCount":13090,"positiveCount":7,"negativeCount":9},{"date":"2012-05-29","volume":7409940,"close":14.52,"clickCount":15809,"positiveCount":3,"negativeCount":14},{"date":"2012-05-30","volume":3693807,"close":14.32,"clickCount":18750,"positiveCount":6,"negativeCount":10},{"date":"2012-05-31","volume":5457203,"close":14.45,"clickCount":10566,"positiveCount":2,"negativeCount":14},{"date":"2012-06-01","volume":6885495,"close":14.82,"clickCount":23562,"positiveCount":4,"negativeCount":12},{"date":"2012-06-04","volume":6198122,"close":14.19,"clickCount":15498,"positiveCount":5,"negativeCount":8},{"date":"2012-06-05","volume":3694321,"close":14.3,"clickCount":3628,"positiveCount":0,"negativeCount":4},{"date":"2012-06-06","volume":6917944,"close":13.94,"clickCount":39277,"positiveCount":10,"negativeCount":31},{"date":"2012-06-07","volume":4720104,"close":13.91,"clickCount":28612,"positiveCount":8,"negativeCount":18},{"date":"2012-06-11","volume":5922393,"close":14.11,"clickCount":20393,"positiveCount":6,"negativeCount":12},{"date":"2012-06-12","volume":3455515,"close":13.92,"clickCount":19932,"positiveCount":5,"negativeCount":11},{"date":"2012-06-13","volume":6376406,"close":14.38,"clickCount":21895,"positiveCount":5,"negativeCount":11},{"date":"2012-06-14","volume":13903541,"close":14.88,"clickCount":33451,"positiveCount":16,"negativeCount":12},{"date":"2012-06-15","volume":7025905,"close":14.75,"clickCount":18241,"positiveCount":9,"negativeCount":14},{"date":"2012-06-18","volume":8205112,"close":15.13,"clickCount":15024,"positiveCount":5,"negativeCount":4},{"date":"2012-06-19","volume":5632092,"close":15.15,"clickCount":15147,"positiveCount":7,"negativeCount":7},{"date":"2012-06-20","volume":4786572,"close":14.88,"clickCount":17415,"positiveCount":4,"negativeCount":10},{"date":"2012-06-21","volume":10640390,"close":15.21,"clickCount":17908,"positiveCount":9,"negativeCount":10},{"date":"2012-06-25","volume":4995375,"close":14.91,"clickCount":9541,"positiveCount":2,"negativeCount":4},{"date":"2012-06-26","volume":4847233,"close":14.62,"clickCount":29252,"positiveCount":3,"negativeCount":7},{"date":"2012-06-27","volume":23084679,"close":13.31,"clickCount":97627,"positiveCount":23,"negativeCount":60},{"date":"2012-06-28","volume":15518661,"close":12.62,"clickCount":61780,"positiveCount":9,"negativeCount":50},{"date":"2012-06-29","volume":7822237,"close":13.01,"clickCount":30673,"positiveCount":12,"negativeCount":16},{"date":"2012-07-02","volume":5969759,"close":13.13,"clickCount":16037,"positiveCount":0,"negativeCount":10},{"date":"2012-07-03","volume":4819148,"close":13.34,"clickCount":47680,"positiveCount":4,"negativeCount":5},{"date":"2012-07-04","volume":2823101,"close":13.09,"clickCount":24606,"positiveCount":7,"negativeCount":9},{"date":"2012-07-05","volume":6701305,"close":12.64,"clickCount":25301,"positiveCount":12,"negativeCount":20},{"date":"2012-07-06","volume":4546679,"close":13.08,"clickCount":15094,"positiveCount":4,"negativeCount":7},{"date":"2012-07-09","volume":8002585,"close":13.22,"clickCount":40682,"positiveCount":7,"negativeCount":11},{"date":"2012-07-10","volume":4320048,"close":13.39,"clickCount":14610,"positiveCount":7,"negativeCount":9},{"date":"2012-07-11","volume":2815590,"close":13.45,"clickCount":17721,"positiveCount":7,"negativeCount":15},{"date":"2012-07-12","volume":4239113,"close":13.62,"clickCount":19813,"positiveCount":4,"negativeCount":13},{"date":"2012-07-13","volume":3870674,"close":13.58,"clickCount":10496,"positiveCount":4,"negativeCount":14},{"date":"2012-07-16","volume":3205906,"close":13.16,"clickCount":10582,"positiveCount":5,"negativeCount":12},{"date":"2012-07-17","volume":5535500,"close":13.15,"clickCount":16997,"positiveCount":9,"negativeCount":14},{"date":"2012-07-18","volume":3363821,"close":13.18,"clickCount":32813,"positiveCount":3,"negativeCount":14},{"date":"2012-07-19","volume":5886886,"close":13.54,"clickCount":3950,"positiveCount":1,"negativeCount":8},{"date":"2012-07-20","volume":3053822,"close":13.45,"clickCount":8621,"positiveCount":4,"negativeCount":12},{"date":"2012-07-23","volume":5085593,"close":13.63,"clickCount":7571,"positiveCount":2,"negativeCount":9},{"date":"2012-07-24","volume":3303954,"close":13.61,"clickCount":8848,"positiveCount":3,"negativeCount":10},{"date":"2012-07-25","volume":5648595,"close":13.72,"clickCount":41555,"positiveCount":8,"negativeCount":41},{"date":"2012-07-26","volume":4373094,"close":13.4,"clickCount":34296,"positiveCount":6,"negativeCount":40},{"date":"2012-07-27","volume":11525975,"close":13.9,"clickCount":40737,"positiveCount":32,"negativeCount":51},{"date":"2012-07-30","volume":15667532,"close":14.28,"clickCount":84545,"positiveCount":14,"negativeCount":18},{"date":"2012-07-31","volume":6919795,"close":14.03,"clickCount":33127,"positiveCount":12,"negativeCount":28},{"date":"2012-08-01","volume":18752700,"close":15.1,"clickCount":56172,"positiveCount":20,"negativeCount":39},{"date":"2012-08-02","volume":17105428,"close":15.48,"clickCount":43851,"positiveCount":17,"negativeCount":37},{"date":"2012-08-03","volume":14476527,"close":15.73,"clickCount":57713,"positiveCount":28,"negativeCount":39},{"date":"2012-08-06","volume":13497123,"close":15.72,"clickCount":30568,"positiveCount":14,"negativeCount":37},{"date":"2012-08-07","volume":27624533,"close":16.84,"clickCount":44783,"positiveCount":25,"negativeCount":49},{"date":"2012-08-08","volume":14498246,"close":16.95,"clickCount":28138,"positiveCount":11,"negativeCount":38},{"date":"2012-08-09","volume":11046200,"close":17.11,"clickCount":30233,"positiveCount":14,"negativeCount":46},{"date":"2012-08-10","volume":8893072,"close":16.73,"clickCount":25515,"positiveCount":12,"negativeCount":37},{"date":"2012-08-13","volume":10015261,"close":16.32,"clickCount":26043,"positiveCount":9,"negativeCount":25},{"date":"2012-08-14","volume":13750546,"close":16.45,"clickCount":8865,"positiveCount":4,"negativeCount":11},{"date":"2012-08-15","volume":5529225,"close":16,"clickCount":9278,"positiveCount":5,"negativeCount":12},{"date":"2012-08-16","volume":6233176,"close":16.09,"clickCount":6880,"positiveCount":2,"negativeCount":12},{"date":"2012-08-17","volume":6100224,"close":16.16,"clickCount":15667,"positiveCount":8,"negativeCount":19},{"date":"2012-08-20","volume":4786117,"close":16.33,"clickCount":27456,"positiveCount":11,"negativeCount":26},{"date":"2012-08-21","volume":12448864,"close":16.94,"clickCount":15011,"positiveCount":10,"negativeCount":16},{"date":"2012-08-22","volume":15521353,"close":17.4,"clickCount":32025,"positiveCount":14,"negativeCount":30},{"date":"2012-08-23","volume":10345612,"close":16.85,"clickCount":25210,"positiveCount":3,"negativeCount":11},{"date":"2012-08-24","volume":11158356,"close":16.07,"clickCount":14814,"positiveCount":15,"negativeCount":9},{"date":"2012-08-27","volume":5925617,"close":16.03,"clickCount":8375,"positiveCount":3,"negativeCount":8},{"date":"2012-08-28","volume":6108772,"close":16.3,"clickCount":22899,"positiveCount":31,"negativeCount":17},{"date":"2012-08-29","volume":6892884,"close":15.54,"clickCount":23872,"positiveCount":18,"negativeCount":21},{"date":"2012-08-30","volume":10247802,"close":15.12,"clickCount":4468,"positiveCount":3,"negativeCount":8},{"date":"2012-08-31","volume":4124670,"close":15.2,"clickCount":8309,"positiveCount":7,"negativeCount":12},{"date":"2012-09-03","volume":9410037,"close":15.84,"clickCount":6284,"positiveCount":3,"negativeCount":8},{"date":"2012-09-04","volume":5504794,"close":15.42,"clickCount":13796,"positiveCount":4,"negativeCount":7},{"date":"2012-09-05","volume":7332613,"close":16.04,"clickCount":7253,"positiveCount":5,"negativeCount":5},{"date":"2012-09-06","volume":4923584,"close":16.12,"clickCount":6539,"positiveCount":2,"negativeCount":8},{"date":"2012-09-07","volume":12261224,"close":16.75,"clickCount":20233,"positiveCount":10,"negativeCount":16},{"date":"2012-09-10","volume":8025226,"close":16.57,"clickCount":1593,"positiveCount":0,"negativeCount":2},{"date":"2012-09-11","volume":11207362,"close":16.71,"clickCount":13067,"positiveCount":13,"negativeCount":17},{"date":"2012-09-12","volume":5245941,"close":16.63,"clickCount":9164,"positiveCount":3,"negativeCount":12},{"date":"2012-09-13","volume":5752849,"close":16.2,"clickCount":14039,"positiveCount":5,"negativeCount":12},{"date":"2012-09-14","volume":6258976,"close":16.31,"clickCount":2076,"positiveCount":1,"negativeCount":2},{"date":"2012-09-17","volume":4189201,"close":15.94,"clickCount":3243,"positiveCount":1,"negativeCount":5},{"date":"2012-09-18","volume":4090769,"close":15.73,"clickCount":2683,"positiveCount":3,"negativeCount":2},{"date":"2012-09-19","volume":2394545,"close":15.94,"clickCount":9434,"positiveCount":2,"negativeCount":10},{"date":"2012-09-20","volume":2962490,"close":15.41,"clickCount":7049,"positiveCount":4,"negativeCount":10},{"date":"2012-09-21","volume":2784643,"close":15.45,"clickCount":691,"positiveCount":0,"negativeCount":1},{"date":"2012-09-24","volume":5127006,"close":16.09,"clickCount":6847,"positiveCount":7,"negativeCount":1},{"date":"2012-09-25","volume":2902965,"close":15.96,"clickCount":1532,"positiveCount":2,"negativeCount":0},{"date":"2012-09-26","volume":2954122,"close":15.51,"clickCount":5016,"positiveCount":3,"negativeCount":3},{"date":"2012-09-27","volume":5419423,"close":16.05,"clickCount":14381,"positiveCount":3,"negativeCount":6},{"date":"2012-09-28","volume":4734332,"close":16.04,"clickCount":4091,"positiveCount":1,"negativeCount":2},{"date":"2012-10-08","volume":2613655,"close":15.88,"clickCount":1896,"positiveCount":0,"negativeCount":4},{"date":"2012-10-09","volume":12472606,"close":16.83,"clickCount":10323,"positiveCount":4,"negativeCount":8},{"date":"2012-10-10","volume":5977394,"close":16.87,"clickCount":8899,"positiveCount":4,"negativeCount":11},{"date":"2012-10-11","volume":4807705,"close":16.61,"clickCount":16705,"positiveCount":1,"negativeCount":7},{"date":"2012-10-12","volume":8570980,"close":16.27,"clickCount":9200,"positiveCount":4,"negativeCount":14},{"date":"2012-10-15","volume":3076136,"close":16.18,"clickCount":12277,"positiveCount":2,"negativeCount":5},{"date":"2012-10-16","volume":3594262,"close":16.27,"clickCount":10087,"positiveCount":2,"negativeCount":8},{"date":"2012-10-17","volume":3619381,"close":16.45,"clickCount":34886,"positiveCount":8,"negativeCount":16},{"date":"2012-10-18","volume":8101164,"close":16.39,"clickCount":18232,"positiveCount":7,"negativeCount":11},{"date":"2012-10-19","volume":7727727,"close":16.14,"clickCount":17515,"positiveCount":4,"negativeCount":8},{"date":"2012-10-22","volume":5056991,"close":16.08,"clickCount":9117,"positiveCount":4,"negativeCount":4},{"date":"2012-10-23","volume":7562524,"close":16.31,"clickCount":13989,"positiveCount":3,"negativeCount":11},{"date":"2012-10-24","volume":3711511,"close":16.42,"clickCount":14786,"positiveCount":2,"negativeCount":6},{"date":"2012-10-25","volume":11213577,"close":16.55,"clickCount":9821,"positiveCount":3,"negativeCount":10},{"date":"2012-10-26","volume":6780593,"close":16.15,"clickCount":4604,"positiveCount":1,"negativeCount":6},{"date":"2012-10-29","volume":6772969,"close":15.62,"clickCount":13263,"positiveCount":4,"negativeCount":12},{"date":"2012-10-30","volume":4156407,"close":15.52,"clickCount":7258,"positiveCount":4,"negativeCount":8},{"date":"2012-10-31","volume":3438162,"close":15.84,"clickCount":6516,"positiveCount":3,"negativeCount":10},{"date":"2012-11-01","volume":4782838,"close":16.15,"clickCount":6884,"positiveCount":0,"negativeCount":8},{"date":"2012-11-02","volume":6928313,"close":16.3,"clickCount":19978,"positiveCount":5,"negativeCount":13},{"date":"2012-11-05","volume":4935386,"close":15.87,"clickCount":8314,"positiveCount":3,"negativeCount":7},{"date":"2012-11-06","volume":4220242,"close":15.91,"clickCount":6440,"positiveCount":2,"negativeCount":6},{"date":"2012-11-07","volume":2710385,"close":15.73,"clickCount":4986,"positiveCount":2,"negativeCount":4},{"date":"2012-11-08","volume":3174405,"close":15.57,"clickCount":941,"positiveCount":2,"negativeCount":0},{"date":"2012-11-09","volume":2025434,"close":15.59,"clickCount":4374,"positiveCount":4,"negativeCount":5},{"date":"2012-11-12","volume":4991434,"close":15.06,"clickCount":8400,"positiveCount":6,"negativeCount":5},{"date":"2012-11-13","volume":5910321,"close":14.82,"clickCount":10956,"positiveCount":5,"negativeCount":8},{"date":"2012-11-14","volume":6270014,"close":14.66,"clickCount":7744,"positiveCount":2,"negativeCount":11},{"date":"2012-11-15","volume":4184062,"close":14.3,"clickCount":7723,"positiveCount":2,"negativeCount":5},{"date":"2012-11-16","volume":4272968,"close":14.35,"clickCount":7818,"positiveCount":4,"negativeCount":6},{"date":"2012-11-19","volume":2794637,"close":14.52,"clickCount":1541,"positiveCount":1,"negativeCount":1},{"date":"2012-11-20","volume":3588802,"close":14.52,"clickCount":6355,"positiveCount":2,"negativeCount":2},{"date":"2012-11-21","volume":2224251,"close":14.58,"clickCount":5747,"positiveCount":4,"negativeCount":10},{"date":"2012-11-22","volume":1590026,"close":14.4,"clickCount":1616,"positiveCount":2,"negativeCount":2},{"date":"2012-11-23","volume":4352140,"close":14.63,"clickCount":3201,"positiveCount":1,"negativeCount":3},{"date":"2012-11-26","volume":3582690,"close":14.64,"clickCount":6580,"positiveCount":1,"negativeCount":5},{"date":"2012-11-27","volume":6838033,"close":13.79,"clickCount":9253,"positiveCount":2,"negativeCount":10},{"date":"2012-11-28","volume":3147057,"close":13.78,"clickCount":5922,"positiveCount":2,"negativeCount":5},{"date":"2012-11-29","volume":2249434,"close":13.47,"clickCount":6636,"positiveCount":2,"negativeCount":9},{"date":"2012-11-30","volume":1740110,"close":13.58,"clickCount":690,"positiveCount":0,"negativeCount":2},{"date":"2012-12-03","volume":3320587,"close":13.4,"clickCount":6097,"positiveCount":5,"negativeCount":10},{"date":"2012-12-04","volume":6945606,"close":13.59,"clickCount":6843,"positiveCount":4,"negativeCount":7},{"date":"2012-12-05","volume":5422507,"close":14.02,"clickCount":5162,"positiveCount":5,"negativeCount":6},{"date":"2012-12-06","volume":6319783,"close":14.24,"clickCount":6342,"positiveCount":2,"negativeCount":10},{"date":"2012-12-07","volume":4227653,"close":14.56,"clickCount":5571,"positiveCount":6,"negativeCount":5},{"date":"2012-12-10","volume":6642101,"close":14.59,"clickCount":1197,"positiveCount":1,"negativeCount":2},{"date":"2012-12-11","volume":2239211,"close":14.46,"clickCount":28193,"positiveCount":6,"negativeCount":1},{"date":"2012-12-12","volume":3504358,"close":14.24,"clickCount":8414,"positiveCount":2,"negativeCount":6},{"date":"2012-12-13","volume":2451295,"close":13.97,"clickCount":13659,"positiveCount":2,"negativeCount":11},{"date":"2012-12-14","volume":10317661,"close":14.9,"clickCount":47759,"positiveCount":4,"negativeCount":11},{"date":"2012-12-17","volume":6938077,"close":14.74,"clickCount":22684,"positiveCount":7,"negativeCount":11},{"date":"2012-12-18","volume":14650997,"close":14.11,"clickCount":25603,"positiveCount":11,"negativeCount":14},{"date":"2012-12-19","volume":9569943,"close":14.28,"clickCount":19879,"positiveCount":11,"negativeCount":6},{"date":"2012-12-20","volume":6595657,"close":14.35,"clickCount":8884,"positiveCount":3,"negativeCount":5},{"date":"2012-12-21","volume":6348861,"close":14.43,"clickCount":20997,"positiveCount":4,"negativeCount":12},{"date":"2012-12-24","volume":14185698,"close":15.06,"clickCount":21118,"positiveCount":6,"negativeCount":15},{"date":"2012-12-25","volume":13097254,"close":15.12,"clickCount":30719,"positiveCount":5,"negativeCount":25},{"date":"2012-12-26","volume":12706821,"close":15.67,"clickCount":23430,"positiveCount":7,"negativeCount":12},{"date":"2012-12-27","volume":8086740,"close":15.48,"clickCount":16187,"positiveCount":2,"negativeCount":7},{"date":"2012-12-28","volume":10289167,"close":15.78,"clickCount":8698,"positiveCount":3,"negativeCount":3},{"date":"2012-12-31","volume":10762159,"close":15.78,"clickCount":24839,"positiveCount":3,"negativeCount":10},{"date":"2013-01-04","volume":9690092,"close":15.94,"clickCount":13795,"positiveCount":4,"negativeCount":6},{"date":"2013-01-07","volume":4283672,"close":15.9,"clickCount":8405,"positiveCount":2,"negativeCount":3},{"date":"2013-01-08","volume":8862491,"close":16.09,"clickCount":16090,"positiveCount":3,"negativeCount":6},{"date":"2013-01-09","volume":5821491,"close":16.02,"clickCount":14930,"positiveCount":2,"negativeCount":4},{"date":"2013-01-10","volume":9258109,"close":15.72,"clickCount":37016,"positiveCount":7,"negativeCount":14},{"date":"2013-01-11","volume":9589369,"close":15.51,"clickCount":16640,"positiveCount":1,"negativeCount":5},{"date":"2013-01-14","volume":12422651,"close":15.92,"clickCount":11236,"positiveCount":3,"negativeCount":6},{"date":"2013-01-15","volume":9039730,"close":15.94,"clickCount":20020,"positiveCount":4,"negativeCount":14},{"date":"2013-01-16","volume":10084662,"close":15.82,"clickCount":4981,"positiveCount":1,"negativeCount":2},{"date":"2013-01-17","volume":6074097,"close":15.71,"clickCount":16349,"positiveCount":2,"negativeCount":8},{"date":"2013-01-18","volume":5484082,"close":15.82,"clickCount":11328,"positiveCount":1,"negativeCount":10},{"date":"2013-01-21","volume":12288761,"close":16.28,"clickCount":11630,"positiveCount":2,"negativeCount":7},{"date":"2013-01-22","volume":9702917,"close":15.97,"clickCount":22947,"positiveCount":8,"negativeCount":5},{"date":"2013-01-23","volume":14655352,"close":16.51,"clickCount":14757,"positiveCount":3,"negativeCount":7},{"date":"2013-01-24","volume":10702290,"close":16.13,"clickCount":9984,"positiveCount":4,"negativeCount":7},{"date":"2013-01-25","volume":15423075,"close":16.74,"clickCount":31862,"positiveCount":5,"negativeCount":15},{"date":"2013-01-28","volume":13806212,"close":17.16,"clickCount":17086,"positiveCount":3,"negativeCount":12},{"date":"2013-01-29","volume":8230119,"close":17.11,"clickCount":22404,"positiveCount":5,"negativeCount":9},{"date":"2013-01-30","volume":9984865,"close":16.84,"clickCount":36052,"positiveCount":8,"negativeCount":34},{"date":"2013-01-31","volume":8359764,"close":16.53,"clickCount":22573,"positiveCount":4,"negativeCount":17},{"date":"2013-02-01","volume":5047918,"close":16.54,"clickCount":39681,"positiveCount":9,"negativeCount":24},{"date":"2013-02-04","volume":5871351,"close":16.32,"clickCount":27334,"positiveCount":3,"negativeCount":8},{"date":"2013-02-05","volume":8302352,"close":17.07,"clickCount":51371,"positiveCount":10,"negativeCount":24},{"date":"2013-02-06","volume":4601210,"close":16.88,"clickCount":24122,"positiveCount":2,"negativeCount":15},{"date":"2013-02-07","volume":4622800,"close":16.91,"clickCount":25461,"positiveCount":8,"negativeCount":6},{"date":"2013-02-08","volume":8106109,"close":17.1,"clickCount":21783,"positiveCount":2,"negativeCount":9},{"date":"2013-02-18","volume":5409565,"close":16.92,"clickCount":31717,"positiveCount":4,"negativeCount":12},{"date":"2013-02-19","volume":8820312,"close":16.98,"clickCount":23061,"positiveCount":6,"negativeCount":11},{"date":"2013-02-20","volume":14260748,"close":17.71,"clickCount":31292,"positiveCount":7,"negativeCount":15},{"date":"2013-02-21","volume":12328578,"close":17.19,"clickCount":17055,"positiveCount":4,"negativeCount":12},{"date":"2013-02-22","volume":14748982,"close":17.82,"clickCount":17816,"positiveCount":6,"negativeCount":13},{"date":"2013-02-25","volume":16104173,"close":18.25,"clickCount":21687,"positiveCount":7,"negativeCount":6},{"date":"2013-02-26","volume":12524523,"close":17.57,"clickCount":32729,"positiveCount":6,"negativeCount":13},{"date":"2013-02-27","volume":7576010,"close":17.56,"clickCount":19482,"positiveCount":2,"negativeCount":8},{"date":"2013-02-28","volume":8037101,"close":18.03,"clickCount":18808,"positiveCount":5,"negativeCount":10},{"date":"2013-03-01","volume":8831870,"close":17.92,"clickCount":9812,"positiveCount":2,"negativeCount":10},{"date":"2013-03-04","volume":16871029,"close":16.84,"clickCount":27104,"positiveCount":3,"negativeCount":13},{"date":"2013-03-05","volume":15340691,"close":16.67,"clickCount":34937,"positiveCount":13,"negativeCount":26},{"date":"2013-03-06","volume":15188567,"close":17.47,"clickCount":31773,"positiveCount":12,"negativeCount":19},{"date":"2013-03-07","volume":10186347,"close":16.83,"clickCount":20671,"positiveCount":7,"negativeCount":8},{"date":"2013-03-08","volume":6601416,"close":16.76,"clickCount":29939,"positiveCount":4,"negativeCount":17},{"date":"2013-03-11","volume":3255115,"close":16.77,"clickCount":22991,"positiveCount":4,"negativeCount":9},{"date":"2013-03-12","volume":11326007,"close":16,"clickCount":19474,"positiveCount":2,"negativeCount":14},{"date":"2013-03-13","volume":10760730,"close":15.49,"clickCount":35235,"positiveCount":4,"negativeCount":26},{"date":"2013-03-14","volume":6325358,"close":15.61,"clickCount":23917,"positiveCount":9,"negativeCount":11},{"date":"2013-03-15","volume":8731391,"close":15.53,"clickCount":22038,"positiveCount":2,"negativeCount":16},{"date":"2013-03-18","volume":9080170,"close":15.95,"clickCount":18117,"positiveCount":7,"negativeCount":15},{"date":"2013-03-19","volume":4640064,"close":16.02,"clickCount":16481,"positiveCount":8,"negativeCount":14},{"date":"2013-03-20","volume":6953868,"close":16.44,"clickCount":16698,"positiveCount":4,"negativeCount":11},{"date":"2013-03-21","volume":6343102,"close":16.51,"clickCount":13630,"positiveCount":7,"negativeCount":8},{"date":"2013-03-22","volume":5589230,"close":16.38,"clickCount":19228,"positiveCount":8,"negativeCount":13},{"date":"2013-03-25","volume":5384464,"close":16.08,"clickCount":7713,"positiveCount":2,"negativeCount":7},{"date":"2013-03-26","volume":7853041,"close":16.21,"clickCount":4629,"positiveCount":2,"negativeCount":6},{"date":"2013-03-27","volume":6073104,"close":15.91,"clickCount":8068,"positiveCount":6,"negativeCount":6},{"date":"2013-03-28","volume":6035407,"close":15.92,"clickCount":16552,"positiveCount":7,"negativeCount":11},{"date":"2013-03-29","volume":10426046,"close":16.59,"clickCount":14917,"positiveCount":6,"negativeCount":21},{"date":"2013-04-01","volume":18974424,"close":17.31,"clickCount":54027,"positiveCount":2,"negativeCount":23},{"date":"2013-04-02","volume":9971464,"close":17.08,"clickCount":22429,"positiveCount":4,"negativeCount":5},{"date":"2013-04-03","volume":7213394,"close":17.1,"clickCount":3952,"positiveCount":1,"negativeCount":3},{"date":"2013-04-08","volume":14716089,"close":17.8,"clickCount":100643,"positiveCount":4,"negativeCount":10},{"date":"2013-04-09","volume":15077621,"close":17.68,"clickCount":31275,"positiveCount":5,"negativeCount":7},{"date":"2013-04-10","volume":13927561,"close":18.01,"clickCount":17053,"positiveCount":3,"negativeCount":9},{"date":"2013-04-11","volume":8195407,"close":17.79,"clickCount":11797,"positiveCount":4,"negativeCount":7},{"date":"2013-04-12","volume":5309861,"close":17.62,"clickCount":13274,"positiveCount":2,"negativeCount":5},{"date":"2013-04-15","volume":5245640,"close":17.81,"clickCount":13139,"positiveCount":3,"negativeCount":7},{"date":"2013-04-16","volume":9279286,"close":17.78,"clickCount":6271,"positiveCount":1,"negativeCount":6},{"date":"2013-04-17","volume":5296507,"close":17.85,"clickCount":12394,"positiveCount":5,"negativeCount":6},{"date":"2013-04-18","volume":15223554,"close":18.24,"clickCount":16513,"positiveCount":6,"negativeCount":6},{"date":"2013-04-19","volume":11938432,"close":18.3,"clickCount":9311,"positiveCount":5,"negativeCount":11},{"date":"2013-04-22","volume":32612505,"close":19.06,"clickCount":18594,"positiveCount":10,"negativeCount":11},{"date":"2013-04-23","volume":15845930,"close":18.36,"clickCount":8751,"positiveCount":4,"negativeCount":11},{"date":"2013-04-24","volume":24524663,"close":19.66,"clickCount":18977,"positiveCount":6,"negativeCount":19},{"date":"2013-04-25","volume":21133877,"close":19.08,"clickCount":9930,"positiveCount":7,"negativeCount":9},{"date":"2013-04-26","volume":10217713,"close":19.1,"clickCount":1560,"positiveCount":2,"negativeCount":1},{"date":"2013-05-02","volume":15401622,"close":20.23,"clickCount":10475,"positiveCount":5,"negativeCount":15},{"date":"2013-05-03","volume":16308527,"close":20.68,"clickCount":13411,"positiveCount":4,"negativeCount":17},{"date":"2013-05-06","volume":21070020,"close":20.94,"clickCount":14025,"positiveCount":13,"negativeCount":17},{"date":"2013-05-07","volume":12828206,"close":20.88,"clickCount":10288,"positiveCount":6,"negativeCount":12},{"date":"2013-05-08","volume":16016400,"close":20.83,"clickCount":29734,"positiveCount":11,"negativeCount":14},{"date":"2013-05-09","volume":22310606,"close":20.86,"clickCount":16589,"positiveCount":16,"negativeCount":22},{"date":"2013-05-10","volume":14874956,"close":20.23,"clickCount":26124,"positiveCount":9,"negativeCount":20},{"date":"2013-05-13","volume":11810597,"close":20.41,"clickCount":20237,"positiveCount":4,"negativeCount":12},{"date":"2013-05-14","volume":10679681,"close":20.19,"clickCount":14218,"positiveCount":4,"negativeCount":15},{"date":"2013-05-15","volume":12571335,"close":20.98,"clickCount":13625,"positiveCount":7,"negativeCount":17},{"date":"2013-05-16","volume":13780588,"close":20.8,"clickCount":41874,"positiveCount":11,"negativeCount":10},{"date":"2013-05-17","volume":23892146,"close":21.91,"clickCount":19303,"positiveCount":9,"negativeCount":17},{"date":"2013-05-20","volume":34736169,"close":24.11,"clickCount":62008,"positiveCount":24,"negativeCount":35},{"date":"2013-05-21","volume":28438579,"close":24.51,"clickCount":16737,"positiveCount":10,"negativeCount":17},{"date":"2013-05-22","volume":18255255,"close":24.7,"clickCount":3171,"positiveCount":4,"negativeCount":0},{"date":"2013-05-23","volume":15291307,"close":24.13,"clickCount":528,"positiveCount":0,"negativeCount":1},{"date":"2013-05-24","volume":14844409,"close":25.03,"clickCount":2460,"positiveCount":2,"negativeCount":0},{"date":"2013-05-27","volume":13117008,"close":25.3,"clickCount":2460,"positiveCount":2,"negativeCount":0},{"date":"2013-05-28","volume":14501339,"close":24.23,"clickCount":493,"positiveCount":0,"negativeCount":1},{"date":"2013-05-29","volume":11873139,"close":24.29,"clickCount":536,"positiveCount":1,"negativeCount":0},{"date":"2013-05-30","volume":9973444,"close":24.28,"clickCount":1150,"positiveCount":1,"negativeCount":1},{"date":"2013-05-31","volume":12390478,"close":23.53,"clickCount":483,"positiveCount":1,"negativeCount":0},{"date":"2013-06-03","volume":13070180,"close":23.02,"clickCount":1293,"positiveCount":0,"negativeCount":1},{"date":"2013-06-04","volume":13653191,"close":22.16,"clickCount":569,"positiveCount":0,"negativeCount":1},{"date":"2013-06-05","volume":14655115,"close":22.64,"clickCount":1548,"positiveCount":0,"negativeCount":2},{"date":"2013-06-06","volume":9797844,"close":22.67,"clickCount":1512,"positiveCount":1,"negativeCount":1},{"date":"2013-06-07","volume":10196503,"close":22.74,"clickCount":3870,"positiveCount":1,"negativeCount":1},{"date":"2013-06-13","volume":17222244,"close":23.92,"clickCount":70780,"positiveCount":13,"negativeCount":28},{"date":"2013-06-14","volume":21464307,"close":24.7,"clickCount":31450,"positiveCount":3,"negativeCount":11},{"date":"2013-06-17","volume":26763680,"close":25.68,"clickCount":63272,"positiveCount":11,"negativeCount":18},{"date":"2013-06-18","volume":14718298,"close":25.58,"clickCount":33601,"positiveCount":3,"negativeCount":10},{"date":"2013-06-19","volume":16000621,"close":25.92,"clickCount":138990,"positiveCount":10,"negativeCount":19},{"date":"2013-06-20","volume":15437858,"close":24.86,"clickCount":57441,"positiveCount":9,"negativeCount":13},{"date":"2013-06-21","volume":12225498,"close":24.91,"clickCount":45724,"positiveCount":11,"negativeCount":13},{"date":"2013-06-24","volume":22853416,"close":24.66,"clickCount":94138,"positiveCount":11,"negativeCount":28},{"date":"2013-06-25","volume":30401123,"close":25.93,"clickCount":78870,"positiveCount":17,"negativeCount":28},{"date":"2013-06-26","volume":32843849,"close":28.53,"clickCount":166730,"positiveCount":23,"negativeCount":35},{"date":"2013-06-27","volume":25613941,"close":28.3,"clickCount":102675,"positiveCount":13,"negativeCount":21},{"date":"2013-06-28","volume":19652049,"close":27.91,"clickCount":94396,"positiveCount":10,"negativeCount":28},{"date":"2013-07-01","volume":21326023,"close":28.92,"clickCount":63693,"positiveCount":8,"negativeCount":16},{"date":"2013-07-02","volume":19856343,"close":28.91,"clickCount":60057,"positiveCount":10,"negativeCount":16},{"date":"2013-07-03","volume":29335365,"close":28.78,"clickCount":70029,"positiveCount":15,"negativeCount":28},{"date":"2013-07-04","volume":19068396,"close":27.73,"clickCount":181759,"positiveCount":13,"negativeCount":28},{"date":"2013-07-05","volume":22051899,"close":26.97,"clickCount":84069,"positiveCount":12,"negativeCount":24},{"date":"2013-07-08","volume":14329957,"close":27.1,"clickCount":61840,"positiveCount":9,"negativeCount":18},{"date":"2013-07-09","volume":12965521,"close":27.6,"clickCount":64110,"positiveCount":11,"negativeCount":25},{"date":"2013-07-10","volume":15009655,"close":27.79,"clickCount":57408,"positiveCount":9,"negativeCount":27},{"date":"2013-07-11","volume":21100525,"close":28.37,"clickCount":110122,"positiveCount":18,"negativeCount":37},{"date":"2013-07-12","volume":29856282,"close":28.53,"clickCount":162041,"positiveCount":31,"negativeCount":35},{"date":"2013-07-15","volume":26157450,"close":30.46,"clickCount":87847,"positiveCount":18,"negativeCount":19},{"date":"2013-07-16","volume":15867484,"close":30.29,"clickCount":68785,"positiveCount":10,"negativeCount":20},{"date":"2013-07-17","volume":13767277,"close":29.32,"clickCount":96190,"positiveCount":17,"negativeCount":40},{"date":"2013-07-18","volume":16021424,"close":30.45,"clickCount":120679,"positiveCount":15,"negativeCount":13},{"date":"2013-07-19","volume":18596728,"close":29.37,"clickCount":84262,"positiveCount":14,"negativeCount":21},{"date":"2013-07-23","volume":21037416,"close":32.32,"clickCount":261311,"positiveCount":36,"negativeCount":67},{"date":"2013-07-24","volume":23875518,"close":33.64,"clickCount":148173,"positiveCount":38,"negativeCount":54},{"date":"2013-07-25","volume":23672596,"close":33.45,"clickCount":108948,"positiveCount":27,"negativeCount":41},{"date":"2013-07-26","volume":13269089,"close":33.37,"clickCount":89277,"positiveCount":18,"negativeCount":23},{"date":"2013-07-29","volume":24697056,"close":33.64,"clickCount":227757,"positiveCount":39,"negativeCount":74},{"date":"2013-07-30","volume":21326746,"close":31.56,"clickCount":216911,"positiveCount":36,"negativeCount":89},{"date":"2013-07-31","volume":15018758,"close":32.86,"clickCount":109427,"positiveCount":30,"negativeCount":56},{"date":"2013-08-01","volume":14830514,"close":34.09,"clickCount":115544,"positiveCount":20,"negativeCount":29},{"date":"2013-08-02","volume":14282373,"close":35.21,"clickCount":137805,"positiveCount":17,"negativeCount":46},{"date":"2013-08-05","volume":8365944,"close":35.2,"clickCount":69919,"positiveCount":12,"negativeCount":16},{"date":"2013-08-06","volume":11127540,"close":34.92,"clickCount":116298,"positiveCount":22,"negativeCount":38},{"date":"2013-08-07","volume":10982881,"close":34.12,"clickCount":81438,"positiveCount":15,"negativeCount":33},{"date":"2013-08-08","volume":12492380,"close":33.09,"clickCount":146644,"positiveCount":21,"negativeCount":59},{"date":"2013-08-09","volume":13267579,"close":32.38,"clickCount":112940,"positiveCount":26,"negativeCount":45},{"date":"2013-08-12","volume":19502039,"close":31.07,"clickCount":132700,"positiveCount":22,"negativeCount":72},{"date":"2013-08-13","volume":14889459,"close":32.26,"clickCount":99573,"positiveCount":19,"negativeCount":41},{"date":"2013-08-14","volume":11166919,"close":32.39,"clickCount":257331,"positiveCount":52,"negativeCount":88},{"date":"2013-08-15","volume":18288450,"close":33.2,"clickCount":197193,"positiveCount":51,"negativeCount":77},{"date":"2013-08-16","volume":16505189,"close":32.23,"clickCount":93563,"positiveCount":22,"negativeCount":32},{"date":"2013-08-19","volume":14181243,"close":33.13,"clickCount":70020,"positiveCount":22,"negativeCount":34},{"date":"2013-08-20","volume":8725975,"close":32.64,"clickCount":74630,"positiveCount":19,"negativeCount":26},{"date":"2013-08-21","volume":8399982,"close":31.73,"clickCount":75573,"positiveCount":19,"negativeCount":28},{"date":"2013-08-22","volume":12190539,"close":33.41,"clickCount":113789,"positiveCount":13,"negativeCount":39},{"date":"2013-08-23","volume":21361749,"close":34.79,"clickCount":95285,"positiveCount":11,"negativeCount":32},{"date":"2013-08-26","volume":11748683,"close":34.87,"clickCount":64528,"positiveCount":17,"negativeCount":17},{"date":"2013-08-27","volume":9985467,"close":35.17,"clickCount":58322,"positiveCount":15,"negativeCount":31},{"date":"2013-08-28","volume":19278017,"close":36.55,"clickCount":109469,"positiveCount":23,"negativeCount":27},{"date":"2013-08-29","volume":12219355,"close":35.36,"clickCount":92441,"positiveCount":28,"negativeCount":39},{"date":"2013-08-30","volume":16897593,"close":31.82,"clickCount":108064,"positiveCount":15,"negativeCount":46},{"date":"2013-09-02","volume":14367744,"close":31.99,"clickCount":98763,"positiveCount":19,"negativeCount":32},{"date":"2013-09-03","volume":9230394,"close":33.13,"clickCount":89227,"positiveCount":14,"negativeCount":35},{"date":"2013-09-04","volume":7495758,"close":32.66,"clickCount":80108,"positiveCount":18,"negativeCount":25},{"date":"2013-09-05","volume":17397061,"close":35.33,"clickCount":82763,"positiveCount":18,"negativeCount":26},{"date":"2013-09-06","volume":16087306,"close":36.22,"clickCount":80300,"positiveCount":9,"negativeCount":20},{"date":"2013-09-09","volume":20058057,"close":35.89,"clickCount":104644,"positiveCount":24,"negativeCount":27},{"date":"2013-09-10","volume":16406735,"close":37.52,"clickCount":70720,"positiveCount":15,"negativeCount":15},{"date":"2013-09-11","volume":16300610,"close":35.25,"clickCount":85576,"positiveCount":17,"negativeCount":28},{"date":"2013-09-12","volume":13189133,"close":35.93,"clickCount":43192,"positiveCount":9,"negativeCount":14},{"date":"2013-09-13","volume":11083970,"close":36.89,"clickCount":56536,"positiveCount":7,"negativeCount":18},{"date":"2013-09-16","volume":23242452,"close":39.45,"clickCount":134419,"positiveCount":22,"negativeCount":35},{"date":"2013-09-17","volume":17504506,"close":39.89,"clickCount":150468,"positiveCount":22,"negativeCount":33},{"date":"2013-09-18","volume":17001168,"close":42.92,"clickCount":168884,"positiveCount":24,"negativeCount":36},{"date":"2013-09-23","volume":18185157,"close":46.37,"clickCount":248951,"positiveCount":42,"negativeCount":47},{"date":"2013-09-24","volume":34891990,"close":51.02,"clickCount":360913,"positiveCount":59,"negativeCount":119},{"date":"2013-09-25","volume":27606503,"close":48.83,"clickCount":471000,"positiveCount":51,"negativeCount":67},{"date":"2013-09-26","volume":30257898,"close":44.57,"clickCount":190375,"positiveCount":28,"negativeCount":99},{"date":"2013-09-27","volume":30825281,"close":47.5,"clickCount":279230,"positiveCount":35,"negativeCount":101},{"date":"2013-09-30","volume":37167716,"close":52.26,"clickCount":371836,"positiveCount":67,"negativeCount":119},{"date":"2013-10-08","volume":35575914,"close":49.21,"clickCount":463603,"positiveCount":74,"negativeCount":123},{"date":"2013-10-09","volume":19426388,"close":49.44,"clickCount":250494,"positiveCount":40,"negativeCount":70},{"date":"2013-10-10","volume":27458429,"close":45.92,"clickCount":207930,"positiveCount":26,"negativeCount":86},{"date":"2013-10-11","volume":19636606,"close":44.99,"clickCount":243527,"positiveCount":23,"negativeCount":68},{"date":"2013-10-14","volume":18159753,"close":46,"clickCount":200463,"positiveCount":29,"negativeCount":59},{"date":"2013-10-15","volume":21514859,"close":46.57,"clickCount":151837,"positiveCount":24,"negativeCount":45},{"date":"2013-10-16","volume":28147962,"close":41.94,"clickCount":176098,"positiveCount":15,"negativeCount":63},{"date":"2013-10-17","volume":18605408,"close":41.04,"clickCount":162880,"positiveCount":16,"negativeCount":37},{"date":"2013-10-18","volume":9794377,"close":41.37,"clickCount":92776,"positiveCount":14,"negativeCount":22},{"date":"2013-10-21","volume":15253169,"close":44.01,"clickCount":103625,"positiveCount":17,"negativeCount":32},{"date":"2013-10-22","volume":24970885,"close":39.6,"clickCount":211725,"positiveCount":32,"negativeCount":49},{"date":"2013-10-23","volume":17172959,"close":39.75,"clickCount":114700,"positiveCount":11,"negativeCount":50},{"date":"2013-10-24","volume":8503494,"close":39.6,"clickCount":76308,"positiveCount":14,"negativeCount":25},{"date":"2013-10-25","volume":20686361,"close":37.83,"clickCount":135623,"positiveCount":12,"negativeCount":54},{"date":"2013-10-28","volume":15138362,"close":37.22,"clickCount":194439,"positiveCount":20,"negativeCount":53},{"date":"2013-10-29","volume":21121873,"close":38.69,"clickCount":147349,"positiveCount":15,"negativeCount":45},{"date":"2013-10-30","volume":21873794,"close":38.9,"clickCount":136270,"positiveCount":18,"negativeCount":30},{"date":"2013-10-31","volume":13183630,"close":36.96,"clickCount":115240,"positiveCount":27,"negativeCount":45},{"date":"2013-11-01","volume":13678350,"close":36.23,"clickCount":96062,"positiveCount":11,"negativeCount":46},{"date":"2013-11-04","volume":8403295,"close":36.15,"clickCount":58673,"positiveCount":7,"negativeCount":27},{"date":"2013-11-05","volume":10267102,"close":37.61,"clickCount":57915,"positiveCount":11,"negativeCount":22},{"date":"2013-11-06","volume":10853311,"close":35.78,"clickCount":50823,"positiveCount":6,"negativeCount":30},{"date":"2013-11-07","volume":9369563,"close":35.44,"clickCount":66704,"positiveCount":14,"negativeCount":29},{"date":"2013-11-08","volume":10354548,"close":35.97,"clickCount":57710,"positiveCount":13,"negativeCount":26},{"date":"2013-11-11","volume":9196428,"close":34.88,"clickCount":86323,"positiveCount":10,"negativeCount":25},{"date":"2013-11-12","volume":9397049,"close":34.99,"clickCount":44558,"positiveCount":7,"negativeCount":20},{"date":"2013-11-13","volume":13557920,"close":35.14,"clickCount":37135,"positiveCount":3,"negativeCount":20},{"date":"2013-11-14","volume":14468565,"close":36.7,"clickCount":48308,"positiveCount":10,"negativeCount":17},{"date":"2013-11-15","volume":22671391,"close":39.03,"clickCount":81131,"positiveCount":17,"negativeCount":12},{"date":"2013-11-18","volume":18741144,"close":39.85,"clickCount":36554,"positiveCount":7,"negativeCount":11},{"date":"2013-11-19","volume":11786116,"close":40.36,"clickCount":53198,"positiveCount":11,"negativeCount":20},{"date":"2013-11-20","volume":7821183,"close":40.4,"clickCount":27162,"positiveCount":7,"negativeCount":12},{"date":"2013-11-21","volume":8915472,"close":41.05,"clickCount":39564,"positiveCount":4,"negativeCount":16},{"date":"2013-11-22","volume":16112340,"close":38.94,"clickCount":113854,"positiveCount":17,"negativeCount":47},{"date":"2013-11-25","volume":12132714,"close":38.22,"clickCount":66272,"positiveCount":14,"negativeCount":19},{"date":"2013-11-26","volume":7692725,"close":38.71,"clickCount":36406,"positiveCount":12,"negativeCount":12},{"date":"2013-11-27","volume":13029603,"close":40.66,"clickCount":37423,"positiveCount":10,"negativeCount":14},{"date":"2013-11-28","volume":8401256,"close":40.56,"clickCount":29052,"positiveCount":5,"negativeCount":17},{"date":"2013-11-29","volume":14128680,"close":42.18,"clickCount":41709,"positiveCount":9,"negativeCount":13},{"date":"2013-12-02","volume":20002317,"close":38.15,"clickCount":77790,"positiveCount":17,"negativeCount":35},{"date":"2013-12-03","volume":17305015,"close":36.9,"clickCount":113083,"positiveCount":22,"negativeCount":45},{"date":"2013-12-04","volume":12817145,"close":37.55,"clickCount":150244,"positiveCount":47,"negativeCount":37},{"date":"2013-12-05","volume":16122789,"close":37.74,"clickCount":128848,"positiveCount":33,"negativeCount":52},{"date":"2013-12-06","volume":10382661,"close":37.86,"clickCount":95064,"positiveCount":13,"negativeCount":47},{"date":"2013-12-09","volume":12714017,"close":39.54,"clickCount":113148,"positiveCount":25,"negativeCount":50},{"date":"2013-12-10","volume":12170438,"close":39.74,"clickCount":59097,"positiveCount":18,"negativeCount":40},{"date":"2013-12-11","volume":10192702,"close":39.92,"clickCount":85490,"positiveCount":15,"negativeCount":32},{"date":"2013-12-12","volume":14726871,"close":40.9,"clickCount":74000,"positiveCount":15,"negativeCount":38},{"date":"2013-12-13","volume":9545835,"close":41.1,"clickCount":56789,"positiveCount":11,"negativeCount":31},{"date":"2013-12-16","volume":8641259,"close":40.71,"clickCount":55224,"positiveCount":13,"negativeCount":24},{"date":"2013-12-17","volume":11257456,"close":38.34,"clickCount":97519,"positiveCount":22,"negativeCount":45},{"date":"2013-12-18","volume":10217554,"close":37.62,"clickCount":53950,"positiveCount":4,"negativeCount":34},{"date":"2013-12-19","volume":6187195,"close":37.51,"clickCount":38666,"positiveCount":6,"negativeCount":19},{"date":"2013-12-20","volume":5884941,"close":37.23,"clickCount":58644,"positiveCount":10,"negativeCount":20},{"date":"2013-12-23","volume":8573659,"close":36.39,"clickCount":44446,"positiveCount":9,"negativeCount":12},{"date":"2013-12-24","volume":13654612,"close":35.72,"clickCount":91370,"positiveCount":19,"negativeCount":47},{"date":"2013-12-25","volume":7440611,"close":36.78,"clickCount":36195,"positiveCount":10,"negativeCount":11},{"date":"2013-12-26","volume":7284235,"close":35.57,"clickCount":60569,"positiveCount":9,"negativeCount":25},{"date":"2013-12-27","volume":7037941,"close":35.67,"clickCount":60349,"positiveCount":8,"negativeCount":28},{"date":"2013-12-30","volume":7561669,"close":37.21,"clickCount":36978,"positiveCount":6,"negativeCount":12},{"date":"2013-12-31","volume":5256303,"close":36.88,"clickCount":30587,"positiveCount":5,"negativeCount":17},{"date":"2014-01-02","volume":9364983,"close":37.03,"clickCount":41529,"positiveCount":3,"negativeCount":21},{"date":"2014-01-03","volume":9625377,"close":37.05,"clickCount":102315,"positiveCount":7,"negativeCount":18},{"date":"2014-01-06","volume":10057066,"close":37.08,"clickCount":60271,"positiveCount":7,"negativeCount":15},{"date":"2014-01-07","volume":23242648,"close":40.19,"clickCount":182306,"positiveCount":38,"negativeCount":72},{"date":"2014-01-08","volume":27213394,"close":42.7,"clickCount":181715,"positiveCount":46,"negativeCount":69},{"date":"2014-01-09","volume":15954243,"close":41.7,"clickCount":80969,"positiveCount":23,"negativeCount":25},{"date":"2014-01-10","volume":11784574,"close":40.22,"clickCount":55471,"positiveCount":8,"negativeCount":29},{"date":"2014-01-13","volume":11057265,"close":40.12,"clickCount":46731,"positiveCount":8,"negativeCount":22},{"date":"2014-01-14","volume":10930534,"close":41.63,"clickCount":38731,"positiveCount":8,"negativeCount":16},{"date":"2014-01-15","volume":10504306,"close":41.92,"clickCount":52233,"positiveCount":7,"negativeCount":20},{"date":"2014-01-16","volume":10081778,"close":40.61,"clickCount":51656,"positiveCount":6,"negativeCount":18},{"date":"2014-01-17","volume":7490265,"close":40.34,"clickCount":35679,"positiveCount":4,"negativeCount":18},{"date":"2014-01-20","volume":8052317,"close":38.8,"clickCount":23457,"positiveCount":4,"negativeCount":10},{"date":"2014-01-21","volume":7512584,"close":40.32,"clickCount":25494,"positiveCount":6,"negativeCount":16},{"date":"2014-01-22","volume":11033465,"close":40.55,"clickCount":39968,"positiveCount":5,"negativeCount":21},{"date":"2014-01-23","volume":20304805,"close":42.82,"clickCount":46551,"positiveCount":12,"negativeCount":22},{"date":"2014-01-24","volume":12662419,"close":41.93,"clickCount":27965,"positiveCount":8,"negativeCount":12},{"date":"2014-01-27","volume":12146344,"close":41.66,"clickCount":16304,"positiveCount":4,"negativeCount":7},{"date":"2014-01-28","volume":13305333,"close":39.85,"clickCount":69919,"positiveCount":12,"negativeCount":35},{"date":"2014-01-29","volume":10343740,"close":40.49,"clickCount":41718,"positiveCount":8,"negativeCount":17},{"date":"2014-01-30","volume":12400890,"close":40.85,"clickCount":29671,"positiveCount":5,"negativeCount":8},{"date":"2014-02-07","volume":16054184,"close":42.22,"clickCount":23042,"positiveCount":8,"negativeCount":3},{"date":"2014-02-10","volume":18508503,"close":43.54,"clickCount":23306,"positiveCount":8,"negativeCount":3},{"date":"2014-02-11","volume":14976692,"close":42.72,"clickCount":27428,"positiveCount":4,"negativeCount":15},{"date":"2014-02-12","volume":10078030,"close":42.93,"clickCount":25180,"positiveCount":9,"negativeCount":9},{"date":"2014-02-13","volume":17632559,"close":40.11,"clickCount":113466,"positiveCount":8,"negativeCount":39},{"date":"2014-02-14","volume":28840509,"close":44.12,"clickCount":117981,"positiveCount":22,"negativeCount":29},{"date":"2014-02-17","volume":22012878,"close":43.05,"clickCount":131461,"positiveCount":49,"negativeCount":72},{"date":"2014-02-18","volume":25707512,"close":44.29,"clickCount":160347,"positiveCount":20,"negativeCount":40},{"date":"2014-02-21","volume":18846447,"close":42.8,"clickCount":281988,"positiveCount":49,"negativeCount":74},{"date":"2014-02-24","volume":12534632,"close":41.67,"clickCount":96867,"positiveCount":24,"negativeCount":43},{"date":"2014-02-25","volume":20619667,"close":39.94,"clickCount":101716,"positiveCount":25,"negativeCount":47},{"date":"2014-02-26","volume":34000899,"close":36.43,"clickCount":280458,"positiveCount":47,"negativeCount":142},{"date":"2014-02-27","volume":29322567,"close":33.84,"clickCount":347528,"positiveCount":62,"negativeCount":161},{"date":"2014-02-28","volume":24740241,"close":35.35,"clickCount":207508,"positiveCount":39,"negativeCount":99},{"date":"2014-03-03","volume":16680740,"close":36.56,"clickCount":81823,"positiveCount":21,"negativeCount":45},{"date":"2014-03-04","volume":11246936,"close":35.73,"clickCount":92871,"positiveCount":21,"negativeCount":70},{"date":"2014-03-05","volume":8510838,"close":34.93,"clickCount":123898,"positiveCount":40,"negativeCount":46},{"date":"2014-03-06","volume":14654962,"close":36.07,"clickCount":137235,"positiveCount":45,"negativeCount":86},{"date":"2014-03-07","volume":12439920,"close":34.38,"clickCount":108147,"positiveCount":23,"negativeCount":75},{"date":"2014-03-10","volume":17400458,"close":31.96,"clickCount":92698,"positiveCount":23,"negativeCount":53},{"date":"2014-03-11","volume":10927653,"close":32.66,"clickCount":46580,"positiveCount":9,"negativeCount":25},{"date":"2014-03-12","volume":10501110,"close":33.6,"clickCount":46035,"positiveCount":14,"negativeCount":18},{"date":"2014-03-13","volume":12339156,"close":34.92,"clickCount":83639,"positiveCount":16,"negativeCount":16},{"date":"2014-03-14","volume":11840389,"close":35.65,"clickCount":60760,"positiveCount":11,"negativeCount":23},{"date":"2014-03-17","volume":9933449,"close":36.64,"clickCount":39554,"positiveCount":6,"negativeCount":12},{"date":"2014-03-18","volume":9883268,"close":36.29,"clickCount":39485,"positiveCount":11,"negativeCount":17},{"date":"2014-03-19","volume":5961623,"close":36.11,"clickCount":62829,"positiveCount":5,"negativeCount":33},{"date":"2014-03-20","volume":9557665,"close":34.25,"clickCount":78972,"positiveCount":14,"negativeCount":28},{"date":"2014-03-21","volume":11223563,"close":35.6,"clickCount":73484,"positiveCount":13,"negativeCount":33},{"date":"2014-03-31","volume":14192950,"close":32.04,"clickCount":258767,"positiveCount":53,"negativeCount":136},{"date":"2014-04-01","volume":7227611,"close":32.18,"clickCount":115326,"positiveCount":28,"negativeCount":57},{"date":"2014-04-02","volume":15960291,"close":31.6,"clickCount":113891,"positiveCount":27,"negativeCount":64},{"date":"2014-04-03","volume":6911022,"close":31.11,"clickCount":36481,"positiveCount":13,"negativeCount":24},{"date":"2014-04-04","volume":5428877,"close":31.69,"clickCount":45531,"positiveCount":5,"negativeCount":25},{"date":"2014-04-08","volume":5888317,"close":32.05,"clickCount":24910,"positiveCount":5,"negativeCount":14},{"date":"2014-04-09","volume":9319478,"close":33,"clickCount":132339,"positiveCount":26,"negativeCount":43},{"date":"2014-04-10","volume":11545022,"close":34.03,"clickCount":67678,"positiveCount":17,"negativeCount":20},{"date":"2014-04-11","volume":11690502,"close":35.24,"clickCount":49823,"positiveCount":13,"negativeCount":8},{"date":"2014-04-14","volume":13964714,"close":36.1,"clickCount":79047,"positiveCount":17,"negativeCount":26},{"date":"2014-04-15","volume":11070459,"close":34.94,"clickCount":86868,"positiveCount":19,"negativeCount":35},{"date":"2014-04-16","volume":12716461,"close":36.58,"clickCount":67135,"positiveCount":8,"negativeCount":21},{"date":"2014-04-17","volume":6497566,"close":36.22,"clickCount":78991,"positiveCount":17,"negativeCount":30},{"date":"2014-04-18","volume":10619800,"close":36.75,"clickCount":66212,"positiveCount":12,"negativeCount":23},{"date":"2014-04-21","volume":7855829,"close":35.74,"clickCount":41809,"positiveCount":7,"negativeCount":12},{"date":"2014-04-22","volume":5513542,"close":35.79,"clickCount":28773,"positiveCount":6,"negativeCount":11},{"date":"2014-04-23","volume":9964846,"close":33.76,"clickCount":58129,"positiveCount":16,"negativeCount":34},{"date":"2014-04-24","volume":7410840,"close":34.11,"clickCount":66174,"positiveCount":16,"negativeCount":37},{"date":"2014-04-25","volume":6192401,"close":34.66,"clickCount":38497,"positiveCount":10,"negativeCount":11},{"date":"2014-04-28","volume":5927511,"close":33.17,"clickCount":66248,"positiveCount":8,"negativeCount":22},{"date":"2014-04-29","volume":4780777,"close":33.91,"clickCount":41184,"positiveCount":11,"negativeCount":18},{"date":"2014-04-30","volume":7411330,"close":33.79,"clickCount":65696,"positiveCount":13,"negativeCount":17},{"date":"2014-05-05","volume":8925437,"close":32.98,"clickCount":54946,"positiveCount":4,"negativeCount":28},{"date":"2014-05-06","volume":12905637,"close":32.49,"clickCount":89925,"positiveCount":16,"negativeCount":46},{"date":"2014-05-07","volume":7532568,"close":32.65,"clickCount":34177,"positiveCount":9,"negativeCount":19},{"date":"2014-05-08","volume":10520068,"close":33.15,"clickCount":30145,"positiveCount":7,"negativeCount":10},{"date":"2014-05-09","volume":6522029,"close":32.76,"clickCount":73846,"positiveCount":7,"negativeCount":13},{"date":"2014-05-12","volume":6377777,"close":33.2,"clickCount":37316,"positiveCount":8,"negativeCount":22},{"date":"2014-05-13","volume":4593354,"close":33.34,"clickCount":30997,"positiveCount":10,"negativeCount":12},{"date":"2014-05-14","volume":4875785,"close":32.84,"clickCount":35259,"positiveCount":9,"negativeCount":11},{"date":"2014-05-15","volume":5772436,"close":32.08,"clickCount":69931,"positiveCount":9,"negativeCount":28},{"date":"2014-05-16","volume":3541545,"close":32.23,"clickCount":30434,"positiveCount":7,"negativeCount":7},{"date":"2014-05-19","volume":3524735,"close":31.8,"clickCount":20604,"positiveCount":4,"negativeCount":7},{"date":"2014-05-20","volume":3098820,"close":31.79,"clickCount":39309,"positiveCount":6,"negativeCount":17},{"date":"2014-05-21","volume":4351181,"close":31.64,"clickCount":45124,"positiveCount":9,"negativeCount":20},{"date":"2014-05-22","volume":6306728,"close":31.81,"clickCount":35778,"positiveCount":3,"negativeCount":19},{"date":"2014-05-23","volume":7540523,"close":32.25,"clickCount":67683,"positiveCount":14,"negativeCount":19},{"date":"2014-05-26","volume":8899369,"close":32.5,"clickCount":54007,"positiveCount":7,"negativeCount":19},{"date":"2014-05-27","volume":5730787,"close":31.96,"clickCount":56918,"positiveCount":11,"negativeCount":15},{"date":"2014-05-28","volume":9617700,"close":31.99,"clickCount":166934,"positiveCount":9,"negativeCount":40},{"date":"2014-11-24","volume":229001,"close":35.19,"clickCount":371270,"positiveCount":60,"negativeCount":132},{"date":"2014-11-25","volume":907903,"close":38.71,"clickCount":355206,"positiveCount":50,"negativeCount":87},{"date":"2014-11-26","volume":84857084,"close":41.91,"clickCount":736395,"positiveCount":74,"negativeCount":201},{"date":"2014-11-27","volume":41043640,"close":40.28,"clickCount":478647,"positiveCount":57,"negativeCount":161},{"date":"2014-11-28","volume":40045878,"close":40.51,"clickCount":280133,"positiveCount":45,"negativeCount":100},{"date":"2014-12-01","volume":30208329,"close":39.08,"clickCount":313838,"positiveCount":38,"negativeCount":106},{"date":"2014-12-02","volume":28181925,"close":39.29,"clickCount":335837,"positiveCount":45,"negativeCount":118},{"date":"2014-12-03","volume":34684126,"close":39.81,"clickCount":210551,"positiveCount":30,"negativeCount":65},{"date":"2014-12-04","volume":26349562,"close":39.95,"clickCount":147101,"positiveCount":21,"negativeCount":77},{"date":"2014-12-05","volume":25596731,"close":38.37,"clickCount":164191,"positiveCount":24,"negativeCount":79},{"date":"2014-12-08","volume":21233059,"close":38.59,"clickCount":164371,"positiveCount":19,"negativeCount":55},{"date":"2014-12-09","volume":39388874,"close":38.26,"clickCount":136317,"positiveCount":17,"negativeCount":54},{"date":"2014-12-10","volume":38891947,"close":40.5,"clickCount":237006,"positiveCount":33,"negativeCount":86},{"date":"2014-12-11","volume":27195168,"close":39.98,"clickCount":134967,"positiveCount":16,"negativeCount":50},{"date":"2014-12-12","volume":14254958,"close":39.92,"clickCount":89972,"positiveCount":16,"negativeCount":33},{"date":"2014-12-15","volume":21793121,"close":40.79,"clickCount":162233,"positiveCount":18,"negativeCount":32},{"date":"2014-12-16","volume":16152838,"close":40.18,"clickCount":188195,"positiveCount":15,"negativeCount":50},{"date":"2014-12-17","volume":19494252,"close":39.08,"clickCount":167933,"positiveCount":26,"negativeCount":66},{"date":"2014-12-18","volume":11528285,"close":39.21,"clickCount":94382,"positiveCount":13,"negativeCount":51},{"date":"2014-12-19","volume":14724965,"close":39.34,"clickCount":99852,"positiveCount":15,"negativeCount":54},{"date":"2014-12-22","volume":17074715,"close":37.47,"clickCount":150763,"positiveCount":21,"negativeCount":62},{"date":"2014-12-23","volume":10118283,"close":37.38,"clickCount":362862,"positiveCount":13,"negativeCount":50},{"date":"2014-12-24","volume":9782479,"close":37.57,"clickCount":70747,"positiveCount":16,"negativeCount":37},{"date":"2014-12-25","volume":12259156,"close":37.81,"clickCount":174423,"positiveCount":30,"negativeCount":105},{"date":"2014-12-26","volume":16230796,"close":38.98,"clickCount":614014,"positiveCount":50,"negativeCount":189},{"date":"2014-12-29","volume":21745161,"close":39.35,"clickCount":245540,"positiveCount":36,"negativeCount":80},{"date":"2014-12-30","volume":17731641,"close":37.68,"clickCount":205751,"positiveCount":30,"negativeCount":79},{"date":"2014-12-31","volume":10307333,"close":37.88,"clickCount":111604,"positiveCount":25,"negativeCount":57},{"date":"2015-01-05","volume":15369287,"close":37.31,"clickCount":210552,"positiveCount":36,"negativeCount":101},{"date":"2015-01-06","volume":18895471,"close":37.02,"clickCount":241407,"positiveCount":38,"negativeCount":127},{"date":"2015-01-07","volume":11717587,"close":37.05,"clickCount":138244,"positiveCount":30,"negativeCount":68},{"date":"2015-01-08","volume":8509313,"close":36.63,"clickCount":117485,"positiveCount":21,"negativeCount":71},{"date":"2015-01-09","volume":9919265,"close":36.4,"clickCount":144144,"positiveCount":21,"negativeCount":75},{"date":"2015-01-12","volume":11349807,"close":37.07,"clickCount":175576,"positiveCount":19,"negativeCount":51},{"date":"2015-01-13","volume":8614830,"close":37.15,"clickCount":84201,"positiveCount":15,"negativeCount":34},{"date":"2015-01-14","volume":6922576,"close":36.58,"clickCount":67576,"positiveCount":12,"negativeCount":41},{"date":"2015-01-15","volume":6708880,"close":36.89,"clickCount":185371,"positiveCount":10,"negativeCount":51},{"date":"2015-01-16","volume":20765301,"close":38.63,"clickCount":219371,"positiveCount":33,"negativeCount":76},{"date":"2015-01-19","volume":16625257,"close":37.32,"clickCount":49768,"positiveCount":9,"negativeCount":23},{"date":"2015-01-20","volume":14954511,"close":38.17,"clickCount":130165,"positiveCount":10,"negativeCount":43},{"date":"2015-01-21","volume":23016882,"close":39.41,"clickCount":127877,"positiveCount":20,"negativeCount":51},{"date":"2015-01-22","volume":29080255,"close":39.67,"clickCount":216197,"positiveCount":32,"negativeCount":88},{"date":"2015-01-23","volume":16427069,"close":39.02,"clickCount":141294,"positiveCount":23,"negativeCount":82},{"date":"2015-01-26","volume":26878950,"close":40.74,"clickCount":152354,"positiveCount":24,"negativeCount":29},{"date":"2015-01-27","volume":25043355,"close":41.2,"clickCount":143864,"positiveCount":21,"negativeCount":31},{"date":"2015-01-28","volume":19821148,"close":40.77,"clickCount":78811,"positiveCount":9,"negativeCount":34},{"date":"2015-01-29","volume":10829864,"close":40.05,"clickCount":138211,"positiveCount":21,"negativeCount":48},{"date":"2015-01-30","volume":9176195,"close":39.72,"clickCount":81136,"positiveCount":10,"negativeCount":43},{"date":"2015-02-02","volume":8092982,"close":39.37,"clickCount":108027,"positiveCount":16,"negativeCount":49},{"date":"2015-02-03","volume":9613926,"close":39.85,"clickCount":103872,"positiveCount":19,"negativeCount":55},{"date":"2015-02-04","volume":15155305,"close":38.79,"clickCount":151920,"positiveCount":34,"negativeCount":125},{"date":"2015-02-05","volume":22083173,"close":39.17,"clickCount":103741,"positiveCount":32,"negativeCount":81},{"date":"2015-02-06","volume":13129031,"close":39.37,"clickCount":149356,"positiveCount":19,"negativeCount":56},{"date":"2015-02-09","volume":8998671,"close":39.3,"clickCount":50027,"positiveCount":14,"negativeCount":23},{"date":"2015-02-10","volume":7966624,"close":39.47,"clickCount":64642,"positiveCount":14,"negativeCount":49},{"date":"2015-02-11","volume":19248211,"close":40.06,"clickCount":188059,"positiveCount":23,"negativeCount":57},{"date":"2015-02-12","volume":15809113,"close":40.05,"clickCount":108612,"positiveCount":18,"negativeCount":59},{"date":"2015-02-13","volume":18509086,"close":40.62,"clickCount":190781,"positiveCount":29,"negativeCount":58},{"date":"2015-02-16","volume":42327278,"close":43.69,"clickCount":232445,"positiveCount":50,"negativeCount":71},{"date":"2015-02-17","volume":23034357,"close":43.03,"clickCount":163297,"positiveCount":23,"negativeCount":43},{"date":"2015-02-25","volume":18713952,"close":41.48,"clickCount":580197,"positiveCount":15,"negativeCount":48},{"date":"2015-02-26","volume":12950824,"close":42.19,"clickCount":55116,"positiveCount":16,"negativeCount":30},{"date":"2015-02-27","volume":14243459,"close":42.33,"clickCount":96224,"positiveCount":19,"negativeCount":36},{"date":"2015-03-02","volume":19391825,"close":42.14,"clickCount":97140,"positiveCount":19,"negativeCount":67},{"date":"2015-03-03","volume":17198955,"close":41.25,"clickCount":236510,"positiveCount":33,"negativeCount":63},{"date":"2015-03-04","volume":30641927,"close":43.3,"clickCount":215065,"positiveCount":32,"negativeCount":75},{"date":"2015-03-05","volume":15165696,"close":42.59,"clickCount":147677,"positiveCount":27,"negativeCount":57},{"date":"2015-03-06","volume":11809888,"close":42.48,"clickCount":237382,"positiveCount":25,"negativeCount":67},{"date":"2015-03-09","volume":15903283,"close":43.2,"clickCount":153232,"positiveCount":24,"negativeCount":68},{"date":"2015-03-10","volume":17406139,"close":43.51,"clickCount":309905,"positiveCount":22,"negativeCount":77},{"date":"2015-03-11","volume":14534729,"close":42.92,"clickCount":128993,"positiveCount":31,"negativeCount":69},{"date":"2015-03-12","volume":11491192,"close":42.72,"clickCount":119195,"positiveCount":18,"negativeCount":75},{"date":"2015-03-13","volume":10105120,"close":42.8,"clickCount":204412,"positiveCount":30,"negativeCount":77},{"date":"2015-03-16","volume":20195503,"close":43.97,"clickCount":360201,"positiveCount":34,"negativeCount":49},{"date":"2015-03-17","volume":21783404,"close":44.52,"clickCount":157305,"positiveCount":21,"negativeCount":70},{"date":"2015-03-18","volume":33790386,"close":48.56,"clickCount":249129,"positiveCount":37,"negativeCount":87},{"date":"2015-03-19","volume":19579808,"close":47.6,"clickCount":288543,"positiveCount":32,"negativeCount":104},{"date":"2015-03-20","volume":25653990,"close":48.29,"clickCount":387858,"positiveCount":40,"negativeCount":105},{"date":"2015-03-23","volume":23567593,"close":49.1,"clickCount":263056,"positiveCount":41,"negativeCount":132},{"date":"2015-03-24","volume":28966726,"close":50.26,"clickCount":209549,"positiveCount":34,"negativeCount":102},{"date":"2015-03-25","volume":19412486,"close":49.87,"clickCount":447868,"positiveCount":54,"negativeCount":139}]